tests/__init__.py
tests/conftest.py
tests/some_test_defs.py
tests/test_able.py
tests/test_fields.py
tests/test_yamliz.py
yamliz/__init__.py
yamliz/_able.py
yamliz/_common.py
yamliz/_exceptions.py
yamliz/_fields.py
yamliz/fields.py
yamliz-0.1.2.dist-info/LICENSE
yamliz-0.1.2.dist-info/METADATA
yamliz-0.1.2.dist-info/WHEEL
yamliz-0.1.2.dist-info/top_level.txt
yamliz-0.1.2.dist-info/RECORD
