Metadata-Version: 2.1
Name: yamliz
Version: 0.1.2
Summary: Dataclasses married with yaml.
Home-page: https://gitlab.com/kamichal/yamliz
Author: Michał Kaczmarczyk
Author-email: michal.s.kaczmarczyk@gmail.com
License: UNKNOWN
Platform: UNKNOWN
Classifier: Development Status :: 3 - Alpha
Classifier: Programming Language :: Python
Classifier: Programming Language :: Python :: 3
Classifier: Programming Language :: Python :: 3.7
Classifier: Operating System :: OS Independent
Requires-Python: >=3.7
Requires-Dist: pyyaml (==5.*)
